{
    "sourceFile": "src/lib/programmes.json",
    "activeCommit": 0,
    "commits": [
        {
            "activePatchIndex": 1,
            "patches": [
                {
                    "date": 1747549194022,
                    "content": "Index: \n===================================================================\n--- \n+++ \n"
                },
                {
                    "date": 1747834680809,
                    "content": "Index: \n===================================================================\n--- \n+++ \n@@ -0,0 +1,104 @@\n+{\n+  \"consultations\": [ \n+    {\n+      \"id\": \"emerging-athlete-development\",\n+      \"title\": \"Emerge: Emerging Athlete Development\",\n+      \"description\": \"Custom programs for young athletes, focusing on skill mastery, nutrition, and injury prevention.\",\n+      \"image\": \"/programmes1.png\",\n+      \"buttonText\": \"Book a Session\",\n+      \"buttonLink\": \"/book/emerging-athlete\",\n+      \"consultations\": [\n+        {\n+          \"id\": \"rehabilitation-programme\",\n+          \"title\": \"Emerging Athlete Development\",\n+          \"intro\": \"High-quality physiotherapy and rehabilitation support for individuals of all ages following injury or surgery.\",\n+          \"details\": \"Using the latest rehabilitation techniques and equipment, our expert team will help you achieve the best outcome.\",\n+          \"idealFor\": \"Young athletes looking to develop skills and prevent injuries.\",\n+          \"bookings\": [\"BOOK ONLINE\"]\n+        },\n+        {\n+          \"id\": \"acl-at-goperform\",\n+          \"title\": \"ACL Rehabilitation\",\n+          \"subtitle\": \"Rehabilitation Packages\",\n+          \"description\": \"Comprehensive rehabilitation from pre-surgery through to full recovery, including non-surgical routes.\",\n+          \"price\": \"Price on Application\",\n+          \"details\": \"Bespoke packages tailored to individual needs, working closely with surgeons and health providers. Book an initial physiotherapy appointment to start.\",\n+          \"extra\": \"Specializing in ACL rehabilitation with decades of experience in professional sport, supporting 15-20 individuals at any time.\",\n+          \"podcastText\": \"Listen to our podcast episode on ACL recovery by searching 'GoPerform Podcast' (episode 12) or below:\",\n+   \n+          \"idealFor\": \"Athletes recovering from ACL or other orthopedic surgeries.\",\n+          \"bookings\": [\"BOOK ONLINE\"]\n+        },\n+        {\n+          \"id\": \"rehab-membership\",\n+          \"title\": \"Rehab Membership\",\n+          \"description\": \"Daily access to facilities and staff for optimal injury recovery.\",\n+          \"price\": \"£445/month\",\n+          \"features\": [\n+            \"Initial physiotherapy assessment\",\n+            \"4 one-to-one physiotherapy sessions per month\",\n+            \"Weekly soft tissue and manual therapy treatment\",\n+            \"Weekly strength and conditioning sessions with our coaches\",\n+            \"Daily access to GoPerform for rehabilitation\",\n+            \"Use of specialist equipment including AlterG, GameReady, Normatec, and Altitude training\",\n+            \"Online support\"\n+          ],\n+          \"idealFor\": \"Individuals aiming for a full return to sports through comprehensive support.\",\n+          \"bookings\": [\"BOOK ONLINE\"]\n+        }\n+      ]\n+    },\n+    {\n+      \"id\": \"elevate-pro-athlete-development\",\n+      \"title\": \"Elevate: Pro Athlete Development\",\n+      \"description\": \"Elite training for top athletes, pushing performance with advanced techniques and mental conditioning.\",\n+      \"image\": \"/programmes2.png\",\n+      \"buttonText\": \"Book a Session\",\n+      \"buttonLink\": \"/book/elevate-pro\",\n+      \"consultations\": [\n+        {\n+          \"id\": \"pro-assessment\",\n+          \"title\": \"Pro Athlete Assessment\",\n+          \"price\": \"£150\",\n+          \"details\": \"Comprehensive assessment of physical and mental performance to create a tailored training plan.\",\n+          \"idealFor\": \"Professional athletes seeking to optimize their performance.\",\n+          \"bookings\": [\"BOOK ONLINE\"]\n+        },\n+        {\n+          \"id\": \"pro-training-program\",\n+          \"title\": \"Pro Training Program\",\n+          \"price\": \"£600/month\",\n+          \"details\": \"Monthly coaching, advanced training sessions, and mental conditioning for elite performance.\",\n+          \"idealFor\": \"Top athletes aiming for competitive excellence.\",\n+          \"bookings\": [\"BOOK ONLINE\"]\n+        }\n+      ]\n+    },\n+    {\n+      \"id\": \"vo2-max-enhancement\",\n+      \"title\": \"VO2 Max Enhancement\",\n+      \"description\": \"Skyrocket your endurance with programs designed to boost cardiovascular efficiency and stamina.\",\n+      \"image\": \"/programmes3.png\",\n+      \"buttonText\": \"Book a Session\",\n+      \"buttonLink\": \"/book/vo2-max\",\n+      \"consultations\": [\n+        {\n+          \"id\": \"vo2-max-test\",\n+          \"title\": \"VO2 Max Test\",\n+          \"price\": \"£120\",\n+          \"details\": \"Measure your aerobic capacity with a detailed report and training recommendations.\",\n+          \"idealFor\": \"Athletes looking to improve endurance and stamina.\",\n+          \"bookings\": [\"BOOK ONLINE\"]\n+        },\n+        {\n+          \"id\": \"endurance-program\",\n+          \"title\": \"Endurance Training Program\",\n+          \"price\": \"£350/month\",\n+          \"details\": \"Monthly VO2 Max tests, weekly training sessions, and personalized endurance plans.\",\n+          \"idealFor\": \"Runners, cyclists, or triathletes aiming for peak cardiovascular performance.\",\n+          \"bookings\": [\"BOOK ONLINE\"]\n+        }\n+      ]\n+    }\n+  ]\n+}\n\\ No newline at end of file\n"
                }
            ],
            "date": 1747549194022,
            "name": "Commit-0",
            "content": "{\n  \"consultations\": [\n    {\n      \"id\": \"emerging-athlete-development\",\n      \"title\": \"Emerge: Emerging Athlete Development\",\n      \"description\": \"Custom programs for young athletes, focusing on skill mastery, nutrition, and injury prevention.\",\n      \"image\": \"/programmes1.png\",\n      \"buttonText\": \"Book a Session\",\n      \"buttonLink\": \"/book/emerging-athlete\",\n      \"consultations\": [\n        {\n          \"id\": \"rehabilitation-programme\",\n          \"title\": \"Emerging Athlete Development\",\n          \"intro\": \"High-quality physiotherapy and rehabilitation support for individuals of all ages following injury or surgery.\",\n          \"details\": \"Using the latest rehabilitation techniques and equipment, our expert team will help you achieve the best outcome.\",\n          \"idealFor\": \"Young athletes looking to develop skills and prevent injuries.\",\n          \"bookings\": [\"BOOK ONLINE\"]\n        },\n        {\n          \"id\": \"acl-at-goperform\",\n          \"title\": \"ACL Rehabilitation\",\n          \"subtitle\": \"Rehabilitation Packages\",\n          \"description\": \"Comprehensive rehabilitation from pre-surgery through to full recovery, including non-surgical routes.\",\n          \"price\": \"Price on Application\",\n          \"details\": \"Bespoke packages tailored to individual needs, working closely with surgeons and health providers. Book an initial physiotherapy appointment to start.\",\n          \"extra\": \"Specializing in ACL rehabilitation with decades of experience in professional sport, supporting 15-20 individuals at any time.\",\n          \"podcastText\": \"Listen to our podcast episode on ACL recovery by searching 'GoPerform Podcast' (episode 12) or below:\",\n          \"podcastEmbed\": \"<iframe src=\\\"https://player.example.com/episode12\\\" width=\\\"100%\\\" height=\\\"200\\\"></iframe>\",\n          \"idealFor\": \"Athletes recovering from ACL or other orthopedic surgeries.\",\n          \"bookings\": [\"BOOK ONLINE\"]\n        },\n        {\n          \"id\": \"rehab-membership\",\n          \"title\": \"Rehab Membership\",\n          \"description\": \"Daily access to facilities and staff for optimal injury recovery.\",\n          \"price\": \"£445/month\",\n          \"features\": [\n            \"Initial physiotherapy assessment\",\n            \"4 one-to-one physiotherapy sessions per month\",\n            \"Weekly soft tissue and manual therapy treatment\",\n            \"Weekly strength and conditioning sessions with our coaches\",\n            \"Daily access to GoPerform for rehabilitation\",\n            \"Use of specialist equipment including AlterG, GameReady, Normatec, and Altitude training\",\n            \"Online support\"\n          ],\n          \"idealFor\": \"Individuals aiming for a full return to sports through comprehensive support.\",\n          \"bookings\": [\"BOOK ONLINE\"]\n        }\n      ]\n    },\n    {\n      \"id\": \"elevate-pro-athlete-development\",\n      \"title\": \"Elevate: Pro Athlete Development\",\n      \"description\": \"Elite training for top athletes, pushing performance with advanced techniques and mental conditioning.\",\n      \"image\": \"/programmes2.png\",\n      \"buttonText\": \"Book a Session\",\n      \"buttonLink\": \"/book/elevate-pro\",\n      \"consultations\": [\n        {\n          \"id\": \"pro-assessment\",\n          \"title\": \"Pro Athlete Assessment\",\n          \"price\": \"£150\",\n          \"details\": \"Comprehensive assessment of physical and mental performance to create a tailored training plan.\",\n          \"idealFor\": \"Professional athletes seeking to optimize their performance.\",\n          \"bookings\": [\"BOOK ONLINE\"]\n        },\n        {\n          \"id\": \"pro-training-program\",\n          \"title\": \"Pro Training Program\",\n          \"price\": \"£600/month\",\n          \"details\": \"Monthly coaching, advanced training sessions, and mental conditioning for elite performance.\",\n          \"idealFor\": \"Top athletes aiming for competitive excellence.\",\n          \"bookings\": [\"BOOK ONLINE\"]\n        }\n      ]\n    },\n    {\n      \"id\": \"vo2-max-enhancement\",\n      \"title\": \"VO2 Max Enhancement\",\n      \"description\": \"Skyrocket your endurance with programs designed to boost cardiovascular efficiency and stamina.\",\n      \"image\": \"/programmes3.png\",\n      \"buttonText\": \"Book a Session\",\n      \"buttonLink\": \"/book/vo2-max\",\n      \"consultations\": [\n        {\n          \"id\": \"vo2-max-test\",\n          \"title\": \"VO2 Max Test\",\n          \"price\": \"£120\",\n          \"details\": \"Measure your aerobic capacity with a detailed report and training recommendations.\",\n          \"idealFor\": \"Athletes looking to improve endurance and stamina.\",\n          \"bookings\": [\"BOOK ONLINE\"]\n        },\n        {\n          \"id\": \"endurance-program\",\n          \"title\": \"Endurance Training Program\",\n          \"price\": \"£350/month\",\n          \"details\": \"Monthly VO2 Max tests, weekly training sessions, and personalized endurance plans.\",\n          \"idealFor\": \"Runners, cyclists, or triathletes aiming for peak cardiovascular performance.\",\n          \"bookings\": [\"BOOK ONLINE\"]\n        }\n      ]\n    }\n  ]\n}"
        }
    ]
}