{
    "sourceFile": "public/data2.json",
    "activeCommit": 0,
    "commits": [
        {
            "activePatchIndex": 6,
            "patches": [
                {
                    "date": 1747906458486,
                    "content": "Index: \n===================================================================\n--- \n+++ \n"
                },
                {
                    "date": 1747908889944,
                    "content": "Index: \n===================================================================\n--- \n+++ \n@@ -1,15 +1,9 @@\n {\n   \"sections\": {\n     \"programmes\": [\n+ \n       {\n-        \"id\": \"rehabilitation-program\",\n-        \"heading\": \"Rehabilitation Programme\",\n-        \"paragraph\": \"Specialist physiotherapy and rehabilitation support for individuals recovering from injury or surgery.\",\n-        \"imageUrl\": \"/pain5.png\",\n-        \"linkText\": \"FIND OUT MORE\"\n-      },\n-      {\n         \"id\": \"pain-management\",\n         \"heading\": \"Pain Management Program\",\n         \"paragraph\": \"Personalized solutions to alleviate chronic and acute pain.\",\n         \"imageUrl\": \"/pain4.png\",\n"
                },
                {
                    "date": 1747909055841,
                    "content": "Index: \n===================================================================\n--- \n+++ \n@@ -22,16 +22,10 @@\n         \"paragraph\": \"Nurture talent and enhance performance.\",\n         \"imageUrl\": \"/pain6.png\",\n         \"linkText\": \"FIND OUT MORE\"\n       },\n+   \n       {\n-        \"id\": \"individual-athlete\",\n-        \"heading\": \"Individual Athlete Development Program\",\n-        \"paragraph\": \"Personalized coaching for athletes.\",\n-        \"imageUrl\": \"/pain3.png\",\n-        \"linkText\": \"FIND OUT MORE\"\n-      },\n-      {\n         \"id\": \"team-athlete\",\n         \"heading\": \"Team Athlete Development Program\",\n         \"paragraph\": \"Elevate team performance through coordinated training.\",\n         \"imageUrl\": \"/pain.png\",\n@@ -118,21 +112,9 @@\n           \"label\": \"DETAILS\",\n           \"paragraphs\": [\"Structured training, nutrition, and recovery plans.\"]\n         }\n       },\n-      \"individual-athlete\": {\n-        \"id\": \"individual-athlete\",\n-        \"title\": \"Individual Athlete Development Program\",\n-        \"description\": [\"Personalized coaching for athletes.\"],\n-        \"price\": {\n-          \"label\": \"PRICE\",\n-          \"value\": \"£POA\"\n-        },\n-        \"details\": {\n-          \"label\": \"DETAILS\",\n-          \"paragraphs\": [\"Sport-specific training and optimization.\"]\n-        }\n-      },\n+\n       \"team-athlete\": {\n         \"id\": \"team-athlete\",\n         \"title\": \"Team Athlete Development Program\",\n         \"description\": [\"Elevates team performance.\"],\n"
                },
                {
                    "date": 1747909170583,
                    "content": "Index: \n===================================================================\n--- \n+++ \n@@ -30,16 +30,10 @@\n         \"paragraph\": \"Elevate team performance through coordinated training.\",\n         \"imageUrl\": \"/pain.png\",\n         \"linkText\": \"FIND OUT MORE\"\n       },\n+ \n       {\n-        \"id\": \"acl-rehab\",\n-        \"heading\": \"ACL Rehabilitation Package\",\n-        \"paragraph\": \"Comprehensive rehab for ACL and other surgeries.\",\n-        \"imageUrl\": \"/acl-rehab.png\",\n-        \"linkText\": \"FIND OUT MORE\"\n-      },\n-      {\n         \"id\": \"rehab-membership\",\n         \"heading\": \"Rehab Membership\",\n         \"paragraph\": \"Daily access to facilities for optimal recovery.\",\n         \"imageUrl\": \"/rehab-membership.png\",\n@@ -126,33 +120,9 @@\n           \"label\": \"DETAILS\",\n           \"paragraphs\": [\"Focuses on teamwork and sport-specific drills.\"]\n         }\n       },\n-      \"aclRehabPackage\": {\n-        \"id\": \"acl-rehab\",\n-        \"title\": \"ACL Rehabilitation Package\",\n-        \"description\": [\n-          \"Comprehensive rehab from pre-surgery to full recovery.\",\n-          \"Also available for non-surgical serious injury recovery.\"\n-        ],\n-        \"price\": {\n-          \"label\": \"PRICE\",\n-          \"value\": \"£POA (single sessions to full packages)\"\n-        },\n-        \"details\": {\n-          \"label\": \"DETAILS\",\n-          \"paragraphs\": [\n-            \"Specialized ACL rehab with decades of experience in professional sports.\",\n-            \"Close collaboration with local and national surgeons.\",\n-            \"Listen to our podcast (GoPerform Podcast, Episode 12) for insights.\"\n-          ]\n-        },\n-        \"podcastEmbed\": {\n-          \"iframeSrc\": \"https://w.soundcloud.com/player/?url=https%3A//api.soundcloud.com/tracks/your-track-id&color=%2300cc66\",\n-          \"width\": \"100%\",\n-          \"height\": 180\n-        }\n-      },\n+     \n       \"rehabMembership\": {\n         \"id\": \"rehab-membership\",\n         \"title\": \"Rehab Membership\",\n         \"description\": [\"Daily access to facilities and staff for optimal recovery.\"],\n"
                },
                {
                    "date": 1747909586751,
                    "content": "Index: \n===================================================================\n--- \n+++ \n@@ -0,0 +1,229 @@\n+{\n+  \"sections\": {\n+    \"programmes\": [\n+      {\n+        \"id\": \"pain-management\",\n+        \"heading\": \"Pain Management Program\",\n+        \"paragraph\": \"Personalized solutions to relieve chronic and acute pain, helping you return to an active lifestyle, whether it’s playing cricket or enjoying daily activities.\",\n+        \"imageUrl\": \"/pain4.png\",\n+        \"linkText\": \"DISCOVER MORE\"\n+      },\n+      {\n+        \"id\": \"strength-enhancement\",\n+        \"heading\": \"Strength Enhancement Program\",\n+        \"paragraph\": \"Build explosive power and resilience for sports like kabaddi, cricket, or your fitness goals.\",\n+        \"imageUrl\": \"/pain2.png\",\n+        \"linkText\": \"DISCOVER MORE\"\n+      },\n+      {\n+        \"id\": \"athlete-development\",\n+        \"heading\": \"Athlete Development Program\",\n+        \"paragraph\": \"Nurture your talent and dominate in sports like badminton, athletics, or marathons.\",\n+        \"imageUrl\": \"/pain6.png\",\n+        \"linkText\": \"DISCOVER MORE\"\n+      },\n+      {\n+        \"id\": \"team-athlete\",\n+        \"heading\": \"Team Athlete Development Program\",\n+        \"paragraph\": \"Elevate your team’s performance with training tailored for cricket, kabaddi, or football.\",\n+        \"imageUrl\": \"/pain.png\",\n+        \"linkText\": \"DISCOVER MORE\"\n+      },\n+      {\n+        \"id\": \"rehab-membership\",\n+        \"heading\": \"Rehab Membership\",\n+        \"paragraph\": \"Daily access to world-class facilities to accelerate recovery and get you back to peak performance.\",\n+        \"imageUrl\": \"/rehab-membership.png\",\n+        \"linkText\": \"DISCOVER MORE\"\n+      },\n+      {\n+        \"id\": \"elevate-program\",\n+        \"heading\": \"Elevate Programme\",\n+        \"paragraph\": \"World-class support to help athletes and fitness enthusiasts achieve their dreams, from cricket pitches to gym floors.\",\n+        \"imageUrl\": \"/elevate-program.png\",\n+        \"linkText\": \"DISCOVER MORE\"\n+      }\n+    ],\n+    \"programDetails\": {\n+      \"rehabilitation-program\": {\n+        \"id\": \"rehabilitation-program\",\n+        \"title\": \"Rehabilitation Programme\",\n+        \"description\": [\n+          \"Recover stronger with our world-class physiotherapy and rehabilitation programme, designed for individuals of all ages healing from injuries or surgeries.\",\n+          \"Inspired by the resilience of Indian athletes, our expert team uses cutting-edge techniques to help you return to sports like cricket or daily activities with confidence.\"\n+        ],\n+        \"price\": {\n+          \"label\": \"PRICE\",\n+          \"value\": \"£POA (Price on Application)\"\n+        },\n+        \"details\": {\n+          \"label\": \"WHAT’S INCLUDED\",\n+          \"paragraphs\": [\n+            \"Personalized recovery plans crafted in collaboration with leading surgeons and healthcare providers to ensure optimal outcomes.\",\n+            \"Ideal for post-surgical recovery or managing injuries from sports like kabaddi, cricket, or daily activities, focusing on restoring strength, mobility, and performance.\",\n+            \"Begin your journey with an initial physiotherapy assessment to create a tailored roadmap to recovery.\"\n+          ]\n+        },\n+        \"idealFor\": {\n+          \"label\": \"IDEAL FOR\",\n+          \"description\": \"Individuals recovering from injuries or surgeries, aiming to return to sports, fitness, or an active lifestyle.\"\n+        }\n+      },\n+      \"pain-management\": {\n+        \"id\": \"pain-management\",\n+        \"title\": \"Pain Management Program\",\n+        \"description\": [\n+          \"Find relief from chronic and acute pain with personalized solutions designed to restore your active lifestyle, whether you’re a weekend cricketer or a fitness enthusiast.\"\n+        ],\n+        \"price\": {\n+          \"label\": \"PRICE\",\n+          \"value\": \"£POA\"\n+        },\n+        \"details\": {\n+          \"label\": \"WHAT’S INCLUDED\",\n+          \"paragraphs\": [\n+            \"Combines advanced diagnostics, hands-on therapy, and minimally invasive techniques to relieve pain and improve mobility.\",\n+            \"Tailored for individuals seeking to manage pain from sports injuries, work-related stress, or chronic conditions, helping you stay active and pain-free.\"\n+          ]\n+        },\n+        \"idealFor\": {\n+          \"label\": \"IDEAL FOR\",\n+          \"description\": \"Anyone seeking relief from pain to enjoy sports, fitness, or daily life without limitations.\"\n+        }\n+      },\n+      \"strength-enhancement\": {\n+        \"id\": \"strength-enhancement\",\n+        \"title\": \"Strength Enhancement Program\",\n+        \"description\": [\n+          \"Build power and resilience to dominate in sports like cricket, kabaddi, or your personal fitness goals with our expert-led programme.\"\n+        ],\n+        \"price\": {\n+          \"label\": \"PRICE\",\n+          \"value\": \"£POA\"\n+        },\n+        \"details\": {\n+          \"label\": \"WHAT’S INCLUDED\",\n+          \"paragraphs\": [\n+            \"Features resistance training, functional workouts, and sport-specific drills to enhance strength and performance.\",\n+            \"Perfect for athletes aiming to improve batting power, sprint speed, or gym performance, with coaching tailored to your goals.\"\n+          ]\n+        },\n+        \"idealFor\": {\n+          \"label\": \"IDEAL FOR\",\n+          \"description\": \"Athletes and fitness enthusiasts looking to boost strength and performance in sports or daily activities.\"\n+        }\n+      },\n+      \"athlete-development\": {\n+        \"id\": \"athlete-development\",\n+        \"title\": \"Athlete Development Program\",\n+        \"description\": [\n+          \"Unleash your potential with a programme designed to nurture talent and elevate performance in sports like badminton, athletics, or marathons.\"\n+        ],\n+        \"price\": {\n+          \"label\": \"PRICE\",\n+          \"value\": \"£POA\"\n+        },\n+        \"details\": {\n+          \"label\": \"WHAT’S INCLUDED\",\n+          \"paragraphs\": [\n+            \"Structured training, personalized nutrition plans, and recovery strategies to help you excel, whether you’re a budding athlete or a seasoned competitor.\",\n+            \"Coaching from experts who’ve trained national and international athletes, tailored to your sport or fitness aspirations.\"\n+          ]\n+        },\n+        \"idealFor\": {\n+          \"label\": \"IDEAL FOR\",\n+          \"description\": \"Aspiring and professional athletes seeking to enhance performance and achieve their sporting dreams.\"\n+        }\n+      },\n+      \"team-athlete\": {\n+        \"id\": \"team-athlete\",\n+        \"title\": \"Team Athlete Development Program\",\n+        \"description\": [\n+          \"Elevate your team’s performance with coordinated training designed for group success in sports like cricket, kabaddi, or football.\"\n+        ],\n+        \"price\": {\n+          \"label\": \"PRICE\",\n+          \"value\": \"£POA\"\n+        },\n+        \"details\": {\n+          \"label\": \"WHAT’S INCLUDED\",\n+          \"paragraphs\": [\n+            \"Focuses on teamwork, sport-specific drills, and conditioning to boost collective performance and strategy.\",\n+            \"Ideal for local sports clubs, school teams, or corporate teams aiming to dominate in competitive play.\"\n+          ]\n+        },\n+        \"idealFor\": {\n+          \"label\": \"IDEAL FOR\",\n+          \"description\": \"Sports teams seeking to improve coordination, strength, and performance in competitive settings.\"\n+        }\n+      },\n+      \"rehabMembership\": {\n+        \"id\": \"rehab-membership\",\n+        \"title\": \"Rehab Membership\",\n+        \"description\": [\n+          \"Accelerate your recovery with daily access to state-of-the-art facilities and expert support, perfect for returning to sports or an active lifestyle.\"\n+        ],\n+        \"price\": {\n+          \"label\": \"PRICE\",\n+          \"value\": \"£445/month\"\n+        },\n+        \"details\": {\n+          \"label\": \"WHAT’S INCLUDED\",\n+          \"items\": [\n+            \"Initial physiotherapy assessment to create a personalized recovery plan\",\n+            \"4 one-to-one physiotherapy sessions per month for hands-on treatment\",\n+            \"Weekly soft tissue and manual therapy to relieve pain and improve mobility\",\n+            \"Weekly strength and conditioning sessions to rebuild strength\",\n+            \"Daily access to GoPerform’s world-class facilities, including gym and recovery zones\",\n+            \"Use of specialist equipment like AlterG anti-gravity treadmill, GameReady, Normatec, Compex, and altitude training systems\",\n+            \"Online support for guidance and progress tracking\"\n+          ]\n+        },\n+        \"idealFor\": {\n+          \"label\": \"IDEAL FOR\",\n+          \"description\": \"Individuals recovering from injuries or surgeries, aiming for a full return to sports like cricket, kabaddi, or fitness activities.\"\n+        }\n+      },\n+      \"elevate-program\": {\n+        \"id\": \"elevate-program\",\n+        \"title\": \"Elevate Programme\",\n+        \"description\": [\n+          \"Join a community of passionate athletes and fitness enthusiasts with world-class support to achieve your training goals, from cricket pitches to gym floors.\",\n+          \"Tailored training, comprehensive support, and no minimum contract – perfect for Indian athletes and fitness lovers.\"\n+        ],\n+        \"price\": {\n+          \"label\": \"PRICE\",\n+          \"value\": \"£195/month\"\n+        },\n+        \"details\": {\n+          \"label\": \"WHAT’S INCLUDED\",\n+          \"items\": [\n+            \"Individually tailored training programme via our app, designed for your goals\",\n+            \"Unlimited group strength & conditioning sessions with expert coaching\",\n+            \"Unlimited group classes (circuits, boxing, Olympic lifting, mobility & core) to enhance versatility\",\n+            \"Regular performance testing (strength, power, body composition) to track your progress\",\n+            \"50% discount on VO2 Max and Resting Metabolic Rate testing for advanced insights\",\n+            \"1x FREE sports massage per month to aid recovery\",\n+            \"Weekly injury drop-in clinics for immediate support\",\n+            \"Full open gym access to our Performance Centre with cutting-edge equipment\",\n+            \"Nutrition consultancy and support to fuel your performance\",\n+            \"20% discount on physiotherapy, soft tissue, and sports massage treatments\",\n+            \"Access to altitude training system and Alter-G anti-gravity treadmill for elite training\",\n+            \"Full use of recovery equipment (Normatec, GameReady, Theragun) for faster recovery\",\n+            \"GoPerform Training T-shirt to represent our community\"\n+          ]\n+        },\n+        \"idealFor\": {\n+          \"label\": \"IDEAL FOR\",\n+          \"description\": \"Athletes, runners, and fitness enthusiasts, from cricketers to marathon runners, seeking structured support to dominate their goals.\"\n+        },\n+        \"testimonial\": {\n+          \"label\": \"TESTIMONIAL\",\n+          \"quote\": \"GoPerform feels like family! The support has taken my cricket game to new heights.\",\n+          \"author\": \"Arjun S.\",\n+          \"role\": \"Amateur Cricketer\"\n+        }\n+      }\n+    }\n+  }\n+}\n\\ No newline at end of file\n"
                },
                {
                    "date": 1747909708894,
                    "content": "Index: \n===================================================================\n--- \n+++ \n@@ -0,0 +1,265 @@\n+{\n+  \"sections\": {\n+    \"programmes\": [\n+      {\n+        \"id\": \"pain-management\",\n+        \"heading\": \"Pain Management Program\",\n+        \"paragraph\": \"Relieve chronic and acute pain with personalized solutions, perfect for staying active in cricket or daily life.\",\n+        \"imageUrl\": \"/pain4.png\",\n+        \"linkText\": \"EXPLORE NOW\"\n+      },\n+      {\n+        \"id\": \"strength-enhancement\",\n+        \"heading\": \"Strength Enhancement Program\",\n+        \"paragraph\": \"Build power and resilience for sports like kabaddi, cricket, or your fitness journey.\",\n+        \"imageUrl\": \"/pain2.png\",\n+        \"linkText\": \"EXPLORE NOW\"\n+      },\n+      {\n+        \"id\": \"athlete-development\",\n+        \"heading\": \"Athlete Development Program\",\n+        \"paragraph\": \"Nurture your talent to excel in badminton, athletics, or marathons with expert coaching.\",\n+        \"imageUrl\": \"/pain6.png\",\n+        \"linkText\": \"EXPLORE NOW\"\n+      },\n+      {\n+        \"id\": \"team-athlete\",\n+        \"heading\": \"Team Athlete Development Program\",\n+        \"paragraph\": \"Elevate your team’s performance in cricket, kabaddi, or football with tailored training.\",\n+        \"imageUrl\": \"/pain.png\",\n+        \"linkText\": \"EXPLORE NOW\"\n+      },\n+      {\n+        \"id\": \"rehab-membership\",\n+        \"heading\": \"Rehab Membership\",\n+        \"paragraph\": \"Accelerate recovery with daily access to world-class facilities, ideal for returning to sports.\",\n+        \"imageUrl\": \"/rehab-membership.png\",\n+        \"linkText\": \"EXPLORE NOW\"\n+      },\n+      {\n+        \"id\": \"elevate-program\",\n+        \"heading\": \"Elevate Programme\",\n+        \"paragraph\": \"World-class support for Indian athletes and fitness enthusiasts to dominate their goals.\",\n+        \"imageUrl\": \"/elevate-program.png\",\n+        \"linkText\": \"EXPLORE NOW\"\n+      }\n+    ],\n+    \"programDetails\": {\n+      \"rehabilitation-program\": {\n+        \"id\": \"rehabilitation-program\",\n+        \"title\": \"Rehabilitation Programme\",\n+        \"description\": [\n+          \"Recover stronger with our world-class physiotherapy and rehabilitation programme, tailored for individuals healing from injuries or surgeries.\",\n+          \"Inspired by the grit of Indian athletes, our expert team uses cutting-edge techniques to help you return to cricket, kabaddi, or daily activities with confidence.\"\n+        ],\n+        \"price\": {\n+          \"label\": \"PRICE\",\n+          \"value\": \"£POA (Price on Application)\"\n+        },\n+        \"details\": {\n+          \"label\": \"WHAT’S INCLUDED\",\n+          \"paragraphs\": [\n+            \"Personalized recovery plans developed with leading surgeons and healthcare providers to ensure optimal outcomes.\",\n+            \"Ideal for post-surgical recovery or managing injuries from sports like cricket, kabaddi, or daily activities, focusing on restoring strength, mobility, and performance.\",\n+            \"Start with an initial physiotherapy assessment to create a tailored roadmap to recovery, designed to get you back to your active lifestyle.\"\n+          ]\n+        },\n+        \"idealFor\": {\n+          \"label\": \"IDEAL FOR\",\n+          \"description\": \"Individuals recovering from injuries or surgeries, aiming to return to sports like cricket or an active lifestyle.\"\n+        },\n+        \"testimonial\": {\n+          \"label\": \"TESTIMONIAL\",\n+          \"quote\": \"The rehabilitation programme got me back on the cricket field faster than I expected!\",\n+          \"author\": \"Vikram P.\",\n+          \"role\": \"Amateur Cricketer\"\n+        }\n+      },\n+      \"pain-management\": {\n+        \"id\": \"pain-management\",\n+        \"title\": \"Pain Management Program\",\n+        \"description\": [\n+          \"Find relief from chronic and acute pain with personalized solutions, helping you stay active in sports or daily life.\"\n+        ],\n+        \"price\": {\n+          \"label\": \"PRICE\",\n+          \"value\": \"£POA\"\n+        },\n+        \"details\": {\n+          \"label\": \"WHAT’S INCLUDED\",\n+          \"paragraphs\": [\n+            \"Advanced diagnostics, hands-on therapy, and minimally invasive techniques to relieve pain and improve mobility.\",\n+            \"Tailored for individuals managing pain from sports injuries, work stress, or chronic conditions, ensuring you can enjoy cricket, kabaddi, or daily activities pain-free.\"\n+          ]\n+        },\n+        \"idealFor\": {\n+          \"label\": \"IDEAL FOR\",\n+          \"description\": \"Anyone seeking relief from pain to enjoy sports, fitness, or daily life without limitations.\"\n+        },\n+        \"testimonial\": {\n+          \"label\": \"TESTIMONIAL\",\n+          \"quote\": \"This programme helped me manage my back pain and get back to playing badminton!\",\n+          \"author\": \"Anjali R.\",\n+          \"role\": \"Badminton Enthusiast\"\n+        }\n+      },\n+      \"strength-enhancement\": {\n+        \"id\": \"strength-enhancement\",\n+        \"title\": \"Strength Enhancement Program\",\n+        \"description\": [\n+          \"Build explosive power and resilience to dominate in sports like cricket, kabaddi, or your personal fitness goals.\"\n+        ],\n+        \"price\": {\n+          \"label\": \"PRICE\",\n+          \"value\": \"£POA\"\n+        },\n+        \"details\": {\n+          \"label\": \"WHAT’S INCLUDED\",\n+          \"paragraphs\": [\n+            \"Resistance training, functional workouts, and sport-specific drills to enhance strength and performance.\",\n+            \"Perfect for athletes aiming to improve batting power, sprint speed, or gym performance, with coaching tailored to your unique goals.\"\n+          ]\n+        },\n+        \"idealFor\": {\n+          \"label\": \"IDEAL FOR\",\n+          \"description\": \"Athletes and fitness enthusiasts looking to boost strength for sports or daily activities.\"\n+        },\n+        \"testimonial\": {\n+          \"label\": \"TESTIMONIAL\",\n+          \"quote\": \"The strength programme gave me the power I needed for my kabaddi raids!\",\n+          \"author\": \"Rahul T.\",\n+          \"role\": \"Kabaddi Player\"\n+        }\n+      },\n+      \"athlete-development\": {\n+        \"id\": \"athlete-development\",\n+        \"title\": \"Athlete Development Program\",\n+        \"description\": [\n+          \"Unleash your potential with a programme designed to nurture talent and elevate performance in sports like badminton, athletics, or marathons.\"\n+        ],\n+        \"price\": {\n+          \"label\": \"PRICE\",\n+          \"value\": \"£POA\"\n+        },\n+        \"details\": {\n+          \"label\": \"WHAT’S INCLUDED\",\n+          \"paragraphs\": [\n+            \"Structured training, personalized nutrition plans, and recovery strategies to help you excel, whether you’re a budding athlete or a seasoned competitor.\",\n+            \"Expert coaching from professionals who’ve trained national and international athletes, tailored to your sport or fitness aspirations.\"\n+          ]\n+        },\n+        \"idealFor\": {\n+          \"label\": \"IDEAL FOR\",\n+          \"description\": \"Aspiring and professional athletes seeking to enhance performance and achieve their sporting dreams.\"\n+        },\n+        \"testimonial\": {\n+          \"label\": \"TESTIMONIAL\",\n+          \"quote\": \"This programme took my marathon running to the next level!\",\n+          \"author\": \"Priya M.\",\n+          \"role\": \"Marathon Runner\"\n+        }\n+      },\n+      \"team-athlete\": {\n+        \"id\": \"team-athlete\",\n+        \"title\": \"Team Athlete Development Program\",\n+        \"description\": [\n+          \"Elevate your team’s performance with coordinated training designed for success in sports like cricket, kabaddi, or football.\"\n+        ],\n+        \"price\": {\n+          \"label\": \"PRICE\",\n+          \"value\": \"£POA\"\n+        },\n+        \"details\": {\n+          \"label\": \"WHAT’S INCLUDED\",\n+          \"paragraphs\": [\n+            \"Team-focused drills, conditioning, and strategy sessions to boost collective performance and unity.\",\n+            \"Ideal for local sports clubs, school teams, or corporate teams aiming to dominate in competitive play.\"\n+          ]\n+        },\n+        \"idealFor\": {\n+          \"label\": \"IDEAL FOR\",\n+          \"description\": \"Sports teams seeking to improve coordination, strength, and performance in competitive settings.\"\n+        },\n+        \"testimonial\": {\n+          \"label\": \"TESTIMONIAL\",\n+          \"quote\": \"Our cricket team’s performance skyrocketed after this programme!\",\n+          \"author\": \"Sanjay K.\",\n+          \"role\": \"Cricket Team Captain\"\n+        }\n+      },\n+      \"rehabMembership\": {\n+        \"id\": \"rehab-membership\",\n+        \"title\": \"Rehab Membership\",\n+        \"description\": [\n+          \"Accelerate your recovery with daily access to state-of-the-art facilities and expert support, perfect for returning to sports like cricket or kabaddi.\"\n+        ],\n+        \"price\": {\n+          \"label\": \"PRICE\",\n+          \"value\": \"£445/month\"\n+        },\n+        \"details\": {\n+          \"label\": \"WHAT’S INCLUDED\",\n+          \"items\": [\n+            \"Initial physiotherapy assessment to create a personalized recovery plan\",\n+            \"4 one-to-one physiotherapy sessions per month for hands-on treatment\",\n+            \"Weekly soft tissue and manual therapy to relieve pain and improve mobility\",\n+            \"Weekly strength and conditioning sessions to rebuild strength\",\n+            \"Daily access to GoPerform’s world-class facilities, including gym and recovery zones\",\n+            \"Use of specialist equipment like AlterG anti-gravity treadmill, GameReady, Normatec, Compex, and altitude training systems\",\n+            \"Online support for guidance and progress tracking\"\n+          ]\n+        },\n+        \"idealFor\": {\n+          \"label\": \"IDEAL FOR\",\n+          \"description\": \"Individuals recovering from injuries or surgeries, aiming to return to sports like cricket, kabaddi, or fitness activities.\"\n+        },\n+        \"testimonial\": {\n+          \"label\": \"TESTIMONIAL\",\n+          \"quote\": \"The rehab membership helped me recover from a knee injury and get back to football!\",\n+          \"author\": \"Amit S.\",\n+          \"role\": \"Football Player\"\n+        }\n+      },\n+      \"elevate-program\": {\n+        \"id\": \"elevate-program\",\n+        \"title\": \"Elevate Programme\",\n+        \"description\": [\n+          \"Join a vibrant community of Indian athletes and fitness enthusiasts with world-class support to achieve your goals, from cricket pitches to gym floors.\",\n+          \"Tailored training, comprehensive support, and no minimum contract – perfect for dominating in sports or personal fitness.\"\n+        ],\n+        \"price\": {\n+          \"label\": \"PRICE\",\n+          \"value\": \"£195/month\"\n+        },\n+        \"details\": {\n+          \"label\": \"WHAT’S INCLUDED\",\n+          \"items\": [\n+            \"Individually tailored training programme via our app, designed for your goals\",\n+            \"Unlimited group strength & conditioning sessions with expert coaching\",\n+            \"Unlimited group classes (circuits, boxing, Olympic lifting, mobility & core) to enhance versatility\",\n+            \"Regular performance testing (strength, power, body composition) to track progress\",\n+            \"50% discount on VO2 Max and Resting Metabolic Rate testing for advanced insights\",\n+            \"1x FREE sports massage per month to aid recovery\",\n+            \"Weekly injury drop-in clinics for immediate support\",\n+            \"Full open gym access to our Performance Centre with cutting-edge equipment\",\n+            \"Nutrition consultancy and support to fuel your performance\",\n+            \"20% discount on physiotherapy, soft tissue, and sports massage treatments\",\n+            \"Access to altitude training system and Alter-G anti-gravity treadmill for elite training\",\n+            \"Full use of recovery equipment (Normatec, GameReady, Theragun) for faster recovery\",\n+            \"GoPerform Training T-shirt to represent our community\"\n+          ]\n+        },\n+        \"idealFor\": {\n+          \"label\": \"IDEAL FOR\",\n+          \"description\": \"Athletes, runners, and fitness enthusiasts, from cricketers to marathon runners, seeking structured support to dominate their goals.\"\n+        },\n+        \"testimonial\": {\n+          \"label\": \"TESTIMONIAL\",\n+          \"quote\": \"GoPerform’s Elevate Programme transformed my cricket game with personalized training and amazing support!\",\n+          \"author\": \"Arjun S.\",\n+          \"role\": \"Amateur Cricketer\"\n+        }\n+      }\n+    }\n+  }\n+}\n\\ No newline at end of file\n"
                },
                {
                    "date": 1747991735263,
                    "content": "Index: \n===================================================================\n--- \n+++ \n@@ -28,16 +28,10 @@\n         \"paragraph\": \"Elevate your team’s performance in cricket, kabaddi, or football with tailored training.\",\n         \"imageUrl\": \"/pain.png\",\n         \"linkText\": \"EXPLORE NOW\"\n       },\n+\n       {\n-        \"id\": \"rehab-membership\",\n-        \"heading\": \"Rehab Membership\",\n-        \"paragraph\": \"Accelerate recovery with daily access to world-class facilities, ideal for returning to sports.\",\n-        \"imageUrl\": \"/rehab-membership.png\",\n-        \"linkText\": \"EXPLORE NOW\"\n-      },\n-      {\n         \"id\": \"elevate-program\",\n         \"heading\": \"Elevate Programme\",\n         \"paragraph\": \"World-class support for Indian athletes and fitness enthusiasts to dominate their goals.\",\n         \"imageUrl\": \"/elevate-program.png\",\n@@ -261,426 +255,5 @@\n         }\n       }\n     }\n   }\n-}\n-{\n-  \"sections\": {\n-    \"programmes\": [\n-      {\n-        \"id\": \"pain-management\",\n-        \"heading\": \"Pain Management Program\",\n-        \"paragraph\": \"Personalized solutions to relieve chronic and acute pain, helping you return to an active lifestyle, whether it’s playing cricket or enjoying daily activities.\",\n-        \"imageUrl\": \"/pain4.png\",\n-        \"linkText\": \"DISCOVER MORE\"\n-      },\n-      {\n-        \"id\": \"strength-enhancement\",\n-        \"heading\": \"Strength Enhancement Program\",\n-        \"paragraph\": \"Build explosive power and resilience for sports like kabaddi, cricket, or your fitness goals.\",\n-        \"imageUrl\": \"/pain2.png\",\n-        \"linkText\": \"DISCOVER MORE\"\n-      },\n-      {\n-        \"id\": \"athlete-development\",\n-        \"heading\": \"Athlete Development Program\",\n-        \"paragraph\": \"Nurture your talent and dominate in sports like badminton, athletics, or marathons.\",\n-        \"imageUrl\": \"/pain6.png\",\n-        \"linkText\": \"DISCOVER MORE\"\n-      },\n-      {\n-        \"id\": \"team-athlete\",\n-        \"heading\": \"Team Athlete Development Program\",\n-        \"paragraph\": \"Elevate your team’s performance with training tailored for cricket, kabaddi, or football.\",\n-        \"imageUrl\": \"/pain.png\",\n-        \"linkText\": \"DISCOVER MORE\"\n-      },\n-      {\n-        \"id\": \"rehab-membership\",\n-        \"heading\": \"Rehab Membership\",\n-        \"paragraph\": \"Daily access to world-class facilities to accelerate recovery and get you back to peak performance.\",\n-        \"imageUrl\": \"/rehab-membership.png\",\n-        \"linkText\": \"DISCOVER MORE\"\n-      },\n-      {\n-        \"id\": \"elevate-program\",\n-        \"heading\": \"Elevate Programme\",\n-        \"paragraph\": \"World-class support to help athletes and fitness enthusiasts achieve their dreams, from cricket pitches to gym floors.\",\n-        \"imageUrl\": \"/elevate-program.png\",\n-        \"linkText\": \"DISCOVER MORE\"\n-      }\n-    ],\n-    \"programDetails\": {\n-      \"rehabilitation-program\": {\n-        \"id\": \"rehabilitation-program\",\n-        \"title\": \"Rehabilitation Programme\",\n-        \"description\": [\n-          \"Recover stronger with our world-class physiotherapy and rehabilitation programme, designed for individuals of all ages healing from injuries or surgeries.\",\n-          \"Inspired by the resilience of Indian athletes, our expert team uses cutting-edge techniques to help you return to sports like cricket or daily activities with confidence.\"\n-        ],\n-        \"price\": {\n-          \"label\": \"PRICE\",\n-          \"value\": \"£POA (Price on Application)\"\n-        },\n-        \"details\": {\n-          \"label\": \"WHAT’S INCLUDED\",\n-          \"paragraphs\": [\n-            \"Personalized recovery plans crafted in collaboration with leading surgeons and healthcare providers to ensure optimal outcomes.\",\n-            \"Ideal for post-surgical recovery or managing injuries from sports like kabaddi, cricket, or daily activities, focusing on restoring strength, mobility, and performance.\",\n-            \"Begin your journey with an initial physiotherapy assessment to create a tailored roadmap to recovery.\"\n-          ]\n-        },\n-        \"idealFor\": {\n-          \"label\": \"IDEAL FOR\",\n-          \"description\": \"Individuals recovering from injuries or surgeries, aiming to return to sports, fitness, or an active lifestyle.\"\n-        }\n-      },\n-      \"pain-management\": {\n-        \"id\": \"pain-management\",\n-        \"title\": \"Pain Management Program\",\n-        \"description\": [\n-          \"Find relief from chronic and acute pain with personalized solutions designed to restore your active lifestyle, whether you’re a weekend cricketer or a fitness enthusiast.\"\n-        ],\n-        \"price\": {\n-          \"label\": \"PRICE\",\n-          \"value\": \"£POA\"\n-        },\n-        \"details\": {\n-          \"label\": \"WHAT’S INCLUDED\",\n-          \"paragraphs\": [\n-            \"Combines advanced diagnostics, hands-on therapy, and minimally invasive techniques to relieve pain and improve mobility.\",\n-            \"Tailored for individuals seeking to manage pain from sports injuries, work-related stress, or chronic conditions, helping you stay active and pain-free.\"\n-          ]\n-        },\n-        \"idealFor\": {\n-          \"label\": \"IDEAL FOR\",\n-          \"description\": \"Anyone seeking relief from pain to enjoy sports, fitness, or daily life without limitations.\"\n-        }\n-      },\n-      \"strength-enhancement\": {\n-        \"id\": \"strength-enhancement\",\n-        \"title\": \"Strength Enhancement Program\",\n-        \"description\": [\n-          \"Build power and resilience to dominate in sports like cricket, kabaddi, or your personal fitness goals with our expert-led programme.\"\n-        ],\n-        \"price\": {\n-          \"label\": \"PRICE\",\n-          \"value\": \"£POA\"\n-        },\n-        \"details\": {\n-          \"label\": \"WHAT’S INCLUDED\",\n-          \"paragraphs\": [\n-            \"Features resistance training, functional workouts, and sport-specific drills to enhance strength and performance.\",\n-            \"Perfect for athletes aiming to improve batting power, sprint speed, or gym performance, with coaching tailored to your goals.\"\n-          ]\n-        },\n-        \"idealFor\": {\n-          \"label\": \"IDEAL FOR\",\n-          \"description\": \"Athletes and fitness enthusiasts looking to boost strength and performance in sports or daily activities.\"\n-        }\n-      },\n-      \"athlete-development\": {\n-        \"id\": \"athlete-development\",\n-        \"title\": \"Athlete Development Program\",\n-        \"description\": [\n-          \"Unleash your potential with a programme designed to nurture talent and elevate performance in sports like badminton, athletics, or marathons.\"\n-        ],\n-        \"price\": {\n-          \"label\": \"PRICE\",\n-          \"value\": \"£POA\"\n-        },\n-        \"details\": {\n-          \"label\": \"WHAT’S INCLUDED\",\n-          \"paragraphs\": [\n-            \"Structured training, personalized nutrition plans, and recovery strategies to help you excel, whether you’re a budding athlete or a seasoned competitor.\",\n-            \"Coaching from experts who’ve trained national and international athletes, tailored to your sport or fitness aspirations.\"\n-          ]\n-        },\n-        \"idealFor\": {\n-          \"label\": \"IDEAL FOR\",\n-          \"description\": \"Aspiring and professional athletes seeking to enhance performance and achieve their sporting dreams.\"\n-        }\n-      },\n-      \"team-athlete\": {\n-        \"id\": \"team-athlete\",\n-        \"title\": \"Team Athlete Development Program\",\n-        \"description\": [\n-          \"Elevate your team’s performance with coordinated training designed for group success in sports like cricket, kabaddi, or football.\"\n-        ],\n-        \"price\": {\n-          \"label\": \"PRICE\",\n-          \"value\": \"£POA\"\n-        },\n-        \"details\": {\n-          \"label\": \"WHAT’S INCLUDED\",\n-          \"paragraphs\": [\n-            \"Focuses on teamwork, sport-specific drills, and conditioning to boost collective performance and strategy.\",\n-            \"Ideal for local sports clubs, school teams, or corporate teams aiming to dominate in competitive play.\"\n-          ]\n-        },\n-        \"idealFor\": {\n-          \"label\": \"IDEAL FOR\",\n-          \"description\": \"Sports teams seeking to improve coordination, strength, and performance in competitive settings.\"\n-        }\n-      },\n-      \"rehabMembership\": {\n-        \"id\": \"rehab-membership\",\n-        \"title\": \"Rehab Membership\",\n-        \"description\": [\n-          \"Accelerate your recovery with daily access to state-of-the-art facilities and expert support, perfect for returning to sports or an active lifestyle.\"\n-        ],\n-        \"price\": {\n-          \"label\": \"PRICE\",\n-          \"value\": \"£445/month\"\n-        },\n-        \"details\": {\n-          \"label\": \"WHAT’S INCLUDED\",\n-          \"items\": [\n-            \"Initial physiotherapy assessment to create a personalized recovery plan\",\n-            \"4 one-to-one physiotherapy sessions per month for hands-on treatment\",\n-            \"Weekly soft tissue and manual therapy to relieve pain and improve mobility\",\n-            \"Weekly strength and conditioning sessions to rebuild strength\",\n-            \"Daily access to GoPerform’s world-class facilities, including gym and recovery zones\",\n-            \"Use of specialist equipment like AlterG anti-gravity treadmill, GameReady, Normatec, Compex, and altitude training systems\",\n-            \"Online support for guidance and progress tracking\"\n-          ]\n-        },\n-        \"idealFor\": {\n-          \"label\": \"IDEAL FOR\",\n-          \"description\": \"Individuals recovering from injuries or surgeries, aiming for a full return to sports like cricket, kabaddi, or fitness activities.\"\n-        }\n-      },\n-      \"elevate-program\": {\n-        \"id\": \"elevate-program\",\n-        \"title\": \"Elevate Programme\",\n-        \"description\": [\n-          \"Join a community of passionate athletes and fitness enthusiasts with world-class support to achieve your training goals, from cricket pitches to gym floors.\",\n-          \"Tailored training, comprehensive support, and no minimum contract – perfect for Indian athletes and fitness lovers.\"\n-        ],\n-        \"price\": {\n-          \"label\": \"PRICE\",\n-          \"value\": \"£195/month\"\n-        },\n-        \"details\": {\n-          \"label\": \"WHAT’S INCLUDED\",\n-          \"items\": [\n-            \"Individually tailored training programme via our app, designed for your goals\",\n-            \"Unlimited group strength & conditioning sessions with expert coaching\",\n-            \"Unlimited group classes (circuits, boxing, Olympic lifting, mobility & core) to enhance versatility\",\n-            \"Regular performance testing (strength, power, body composition) to track your progress\",\n-            \"50% discount on VO2 Max and Resting Metabolic Rate testing for advanced insights\",\n-            \"1x FREE sports massage per month to aid recovery\",\n-            \"Weekly injury drop-in clinics for immediate support\",\n-            \"Full open gym access to our Performance Centre with cutting-edge equipment\",\n-            \"Nutrition consultancy and support to fuel your performance\",\n-            \"20% discount on physiotherapy, soft tissue, and sports massage treatments\",\n-            \"Access to altitude training system and Alter-G anti-gravity treadmill for elite training\",\n-            \"Full use of recovery equipment (Normatec, GameReady, Theragun) for faster recovery\",\n-            \"GoPerform Training T-shirt to represent our community\"\n-          ]\n-        },\n-        \"idealFor\": {\n-          \"label\": \"IDEAL FOR\",\n-          \"description\": \"Athletes, runners, and fitness enthusiasts, from cricketers to marathon runners, seeking structured support to dominate their goals.\"\n-        },\n-        \"testimonial\": {\n-          \"label\": \"TESTIMONIAL\",\n-          \"quote\": \"GoPerform feels like family! The support has taken my cricket game to new heights.\",\n-          \"author\": \"Arjun S.\",\n-          \"role\": \"Amateur Cricketer\"\n-        }\n-      }\n-    }\n-  }\n-}\n-{\n-  \"sections\": {\n-    \"programmes\": [\n- \n-      {\n-        \"id\": \"pain-management\",\n-        \"heading\": \"Pain Management Program\",\n-        \"paragraph\": \"Personalized solutions to alleviate chronic and acute pain.\",\n-        \"imageUrl\": \"/pain4.png\",\n-        \"linkText\": \"FIND OUT MORE\"\n-      },\n-      {\n-        \"id\": \"strength-enhancement\",\n-        \"heading\": \"Strength Enhancement Program\",\n-        \"paragraph\": \"Boost physical performance and build strength.\",\n-        \"imageUrl\": \"/pain2.png\",\n-        \"linkText\": \"FIND OUT MORE\"\n-      },\n-      {\n-        \"id\": \"athlete-development\",\n-        \"heading\": \"Athlete Development Program\",\n-        \"paragraph\": \"Nurture talent and enhance performance.\",\n-        \"imageUrl\": \"/pain6.png\",\n-        \"linkText\": \"FIND OUT MORE\"\n-      },\n-   \n-      {\n-        \"id\": \"team-athlete\",\n-        \"heading\": \"Team Athlete Development Program\",\n-        \"paragraph\": \"Elevate team performance through coordinated training.\",\n-        \"imageUrl\": \"/pain.png\",\n-        \"linkText\": \"FIND OUT MORE\"\n-      },\n- \n-      {\n-        \"id\": \"rehab-membership\",\n-        \"heading\": \"Rehab Membership\",\n-        \"paragraph\": \"Daily access to facilities for optimal recovery.\",\n-        \"imageUrl\": \"/rehab-membership.png\",\n-        \"linkText\": \"FIND OUT MORE\"\n-      },\n-      {\n-        \"id\": \"elevate-program\",\n-        \"heading\": \"Elevate Programme\",\n-        \"paragraph\": \"World-class support for athletes and fitness enthusiasts.\",\n-        \"imageUrl\": \"/elevate-program.png\",\n-        \"linkText\": \"FIND OUT MORE\"\n-      }\n-    ],\n-    \"programDetails\": {\n-      \"rehabilitation-program\": {\n-        \"id\": \"rehabilitation-program\",\n-        \"title\": \"Rehabilitation Programme\",\n-        \"description\": [\n-          \"We provide high-quality physiotherapy and rehabilitation for individuals of all ages recovering from injury or orthopaedic surgery.\",\n-          \"Our expert team uses cutting-edge techniques and equipment to ensure the best outcomes, tailored to your needs.\"\n-        ],\n-        \"price\": {\n-          \"label\": \"PRICE\",\n-          \"value\": \"£POA (Price on Application)\"\n-        },\n-        \"details\": {\n-          \"label\": \"DETAILS\",\n-          \"paragraphs\": [\n-            \"We collaborate with surgeons and healthcare providers to create bespoke rehabilitation plans.\",\n-            \"Suitable for post-surgical or non-surgical recovery, with a focus on restoring function and performance.\",\n-            \"Book an initial physiotherapy assessment to begin your recovery journey.\"\n-          ]\n-        }\n-      },\n-      \"pain-management\": {\n-        \"id\": \"pain-management\",\n-        \"title\": \"Pain Management Program\",\n-        \"description\": [\"Personalized solutions for chronic and acute pain.\"],\n-        \"price\": {\n-          \"label\": \"PRICE\",\n-          \"value\": \"£POA\"\n-        },\n-        \"details\": {\n-          \"label\": \"DETAILS\",\n-          \"paragraphs\": [\"Combines diagnostics, therapy, and minimally invasive techniques.\"]\n-        }\n-      },\n-      \"strength-enhancement\": {\n-        \"id\": \"strength-enhancement\",\n-        \"title\": \"Strength Enhancement Program\",\n-        \"description\": [\"Boost performance and overall strength.\"],\n-        \"price\": {\n-          \"label\": \"PRICE\",\n-          \"value\": \"£POA\"\n-        },\n-        \"details\": {\n-          \"label\": \"DETAILS\",\n-          \"paragraphs\": [\"Includes resistance training and functional workouts.\"]\n-        }\n-      },\n-      \"athlete-development\": {\n-        \"id\": \"athlete-development\",\n-        \"title\": \"Athlete Development Program\",\n-        \"description\": [\"Nurtures talent and enhances performance.\"],\n-        \"price\": {\n-          \"label\": \"PRICE\",\n-          \"value\": \"£POA\"\n-        },\n-        \"details\": {\n-          \"label\": \"DETAILS\",\n-          \"paragraphs\": [\"Structured training, nutrition, and recovery plans.\"]\n-        }\n-      },\n-\n-      \"team-athlete\": {\n-        \"id\": \"team-athlete\",\n-        \"title\": \"Team Athlete Development Program\",\n-        \"description\": [\"Elevates team performance.\"],\n-        \"price\": {\n-          \"label\": \"PRICE\",\n-          \"value\": \"£POA\"\n-        },\n-        \"details\": {\n-          \"label\": \"DETAILS\",\n-          \"paragraphs\": [\"Focuses on teamwork and sport-specific drills.\"]\n-        }\n-      },\n-     \n-      \"rehabMembership\": {\n-        \"id\": \"rehab-membership\",\n-        \"title\": \"Rehab Membership\",\n-        \"description\": [\"Daily access to facilities and staff for optimal recovery.\"],\n-        \"price\": {\n-          \"label\": \"PRICE\",\n-          \"value\": \"£445/month\"\n-        },\n-        \"details\": {\n-          \"label\": \"DETAILS\",\n-          \"items\": [\n-            \"Initial physiotherapy assessment\",\n-            \"4 one-to-one physiotherapy sessions per month\",\n-            \"Weekly soft tissue and manual therapy\",\n-            \"Weekly strength and conditioning sessions\",\n-            \"Daily access to GoPerform facilities\",\n-            \"Use of specialist equipment (AlterG, GameReady, Normatec, Compex, Altitude training)\",\n-            \"Online support\"\n-          ]\n-        },\n-        \"idealFor\": {\n-          \"label\": \"IDEAL FOR\",\n-          \"description\": \"Individuals aiming for a full return to sports and competition.\"\n-        }\n-      },\n-      \"elevate-program\": {\n-        \"id\": \"elevate-program\",\n-        \"title\": \"Elevate Programme\",\n-        \"description\": [\n-          \"World-class support for athletes and fitness enthusiasts to achieve their training goals.\",\n-          \"Tailored training and comprehensive support with no minimum contract.\"\n-        ],\n-        \"price\": {\n-          \"label\": \"PRICE\",\n-          \"value\": \"£195/month\"\n-        },\n-        \"details\": {\n-          \"label\": \"WHAT'S INCLUDED\",\n-          \"items\": [\n-            \"Individually tailored training programme via our app\",\n-            \"Unlimited group strength & conditioning sessions\",\n-            \"Unlimited group classes (circuits, boxing, Olympic lifting, mobility & core)\",\n-            \"Regular performance testing (strength, power, body composition)\",\n-            \"50% discount on VO2 Max and Resting Metabolic Rate testing\",\n-            \"1x FREE sports massage per month\",\n-            \"Weekly injury drop-in clinics\",\n-            \"Full open gym access to our Performance Centre\",\n-            \"Nutrition consultancy and support\",\n-            \"20% discount on physiotherapy, soft tissue, and sports massage\",\n-            \"Access to altitude training system and Alter-G treadmill\",\n-            \"Full use of recovery equipment (Normatec, GameReady, Theragun)\",\n-            \"GoPerform Training T-shirt\"\n-          ]\n-        },\n-        \"idealFor\": {\n-          \"label\": \"IDEAL FOR\",\n-          \"description\": \"Athletes, runners, and fitness enthusiasts seeking structured support.\"\n-        },\n-        \"testimonial\": {\n-          \"label\": \"TESTIMONIAL\",\n-          \"quote\": \"There is nowhere else like it in the area... the support is amazing\",\n-          \"author\": \"Elsa C.\",\n-          \"role\": \"Personal Trainer | Runner\"\n-        }\n-      }\n-    }\n-  }\n }\n\\ No newline at end of file\n"
                }
            ],
            "date": 1747906458486,
            "name": "Commit-0",
            "content": "{\n  \"sections\": {\n    \"programmes\": [\n      {\n        \"id\": \"rehabilitation-program\",\n        \"heading\": \"Rehabilitation Programme\",\n        \"paragraph\": \"Specialist physiotherapy and rehabilitation support for individuals recovering from injury or surgery.\",\n        \"imageUrl\": \"/pain5.png\",\n        \"linkText\": \"FIND OUT MORE\"\n      },\n      {\n        \"id\": \"pain-management\",\n        \"heading\": \"Pain Management Program\",\n        \"paragraph\": \"Personalized solutions to alleviate chronic and acute pain.\",\n        \"imageUrl\": \"/pain4.png\",\n        \"linkText\": \"FIND OUT MORE\"\n      },\n      {\n        \"id\": \"strength-enhancement\",\n        \"heading\": \"Strength Enhancement Program\",\n        \"paragraph\": \"Boost physical performance and build strength.\",\n        \"imageUrl\": \"/pain2.png\",\n        \"linkText\": \"FIND OUT MORE\"\n      },\n      {\n        \"id\": \"athlete-development\",\n        \"heading\": \"Athlete Development Program\",\n        \"paragraph\": \"Nurture talent and enhance performance.\",\n        \"imageUrl\": \"/pain6.png\",\n        \"linkText\": \"FIND OUT MORE\"\n      },\n      {\n        \"id\": \"individual-athlete\",\n        \"heading\": \"Individual Athlete Development Program\",\n        \"paragraph\": \"Personalized coaching for athletes.\",\n        \"imageUrl\": \"/pain3.png\",\n        \"linkText\": \"FIND OUT MORE\"\n      },\n      {\n        \"id\": \"team-athlete\",\n        \"heading\": \"Team Athlete Development Program\",\n        \"paragraph\": \"Elevate team performance through coordinated training.\",\n        \"imageUrl\": \"/pain.png\",\n        \"linkText\": \"FIND OUT MORE\"\n      },\n      {\n        \"id\": \"acl-rehab\",\n        \"heading\": \"ACL Rehabilitation Package\",\n        \"paragraph\": \"Comprehensive rehab for ACL and other surgeries.\",\n        \"imageUrl\": \"/acl-rehab.png\",\n        \"linkText\": \"FIND OUT MORE\"\n      },\n      {\n        \"id\": \"rehab-membership\",\n        \"heading\": \"Rehab Membership\",\n        \"paragraph\": \"Daily access to facilities for optimal recovery.\",\n        \"imageUrl\": \"/rehab-membership.png\",\n        \"linkText\": \"FIND OUT MORE\"\n      },\n      {\n        \"id\": \"elevate-program\",\n        \"heading\": \"Elevate Programme\",\n        \"paragraph\": \"World-class support for athletes and fitness enthusiasts.\",\n        \"imageUrl\": \"/elevate-program.png\",\n        \"linkText\": \"FIND OUT MORE\"\n      }\n    ],\n    \"programDetails\": {\n      \"rehabilitation-program\": {\n        \"id\": \"rehabilitation-program\",\n        \"title\": \"Rehabilitation Programme\",\n        \"description\": [\n          \"We provide high-quality physiotherapy and rehabilitation for individuals of all ages recovering from injury or orthopaedic surgery.\",\n          \"Our expert team uses cutting-edge techniques and equipment to ensure the best outcomes, tailored to your needs.\"\n        ],\n        \"price\": {\n          \"label\": \"PRICE\",\n          \"value\": \"£POA (Price on Application)\"\n        },\n        \"details\": {\n          \"label\": \"DETAILS\",\n          \"paragraphs\": [\n            \"We collaborate with surgeons and healthcare providers to create bespoke rehabilitation plans.\",\n            \"Suitable for post-surgical or non-surgical recovery, with a focus on restoring function and performance.\",\n            \"Book an initial physiotherapy assessment to begin your recovery journey.\"\n          ]\n        }\n      },\n      \"pain-management\": {\n        \"id\": \"pain-management\",\n        \"title\": \"Pain Management Program\",\n        \"description\": [\"Personalized solutions for chronic and acute pain.\"],\n        \"price\": {\n          \"label\": \"PRICE\",\n          \"value\": \"£POA\"\n        },\n        \"details\": {\n          \"label\": \"DETAILS\",\n          \"paragraphs\": [\"Combines diagnostics, therapy, and minimally invasive techniques.\"]\n        }\n      },\n      \"strength-enhancement\": {\n        \"id\": \"strength-enhancement\",\n        \"title\": \"Strength Enhancement Program\",\n        \"description\": [\"Boost performance and overall strength.\"],\n        \"price\": {\n          \"label\": \"PRICE\",\n          \"value\": \"£POA\"\n        },\n        \"details\": {\n          \"label\": \"DETAILS\",\n          \"paragraphs\": [\"Includes resistance training and functional workouts.\"]\n        }\n      },\n      \"athlete-development\": {\n        \"id\": \"athlete-development\",\n        \"title\": \"Athlete Development Program\",\n        \"description\": [\"Nurtures talent and enhances performance.\"],\n        \"price\": {\n          \"label\": \"PRICE\",\n          \"value\": \"£POA\"\n        },\n        \"details\": {\n          \"label\": \"DETAILS\",\n          \"paragraphs\": [\"Structured training, nutrition, and recovery plans.\"]\n        }\n      },\n      \"individual-athlete\": {\n        \"id\": \"individual-athlete\",\n        \"title\": \"Individual Athlete Development Program\",\n        \"description\": [\"Personalized coaching for athletes.\"],\n        \"price\": {\n          \"label\": \"PRICE\",\n          \"value\": \"£POA\"\n        },\n        \"details\": {\n          \"label\": \"DETAILS\",\n          \"paragraphs\": [\"Sport-specific training and optimization.\"]\n        }\n      },\n      \"team-athlete\": {\n        \"id\": \"team-athlete\",\n        \"title\": \"Team Athlete Development Program\",\n        \"description\": [\"Elevates team performance.\"],\n        \"price\": {\n          \"label\": \"PRICE\",\n          \"value\": \"£POA\"\n        },\n        \"details\": {\n          \"label\": \"DETAILS\",\n          \"paragraphs\": [\"Focuses on teamwork and sport-specific drills.\"]\n        }\n      },\n      \"aclRehabPackage\": {\n        \"id\": \"acl-rehab\",\n        \"title\": \"ACL Rehabilitation Package\",\n        \"description\": [\n          \"Comprehensive rehab from pre-surgery to full recovery.\",\n          \"Also available for non-surgical serious injury recovery.\"\n        ],\n        \"price\": {\n          \"label\": \"PRICE\",\n          \"value\": \"£POA (single sessions to full packages)\"\n        },\n        \"details\": {\n          \"label\": \"DETAILS\",\n          \"paragraphs\": [\n            \"Specialized ACL rehab with decades of experience in professional sports.\",\n            \"Close collaboration with local and national surgeons.\",\n            \"Listen to our podcast (GoPerform Podcast, Episode 12) for insights.\"\n          ]\n        },\n        \"podcastEmbed\": {\n          \"iframeSrc\": \"https://w.soundcloud.com/player/?url=https%3A//api.soundcloud.com/tracks/your-track-id&color=%2300cc66\",\n          \"width\": \"100%\",\n          \"height\": 180\n        }\n      },\n      \"rehabMembership\": {\n        \"id\": \"rehab-membership\",\n        \"title\": \"Rehab Membership\",\n        \"description\": [\"Daily access to facilities and staff for optimal recovery.\"],\n        \"price\": {\n          \"label\": \"PRICE\",\n          \"value\": \"£445/month\"\n        },\n        \"details\": {\n          \"label\": \"DETAILS\",\n          \"items\": [\n            \"Initial physiotherapy assessment\",\n            \"4 one-to-one physiotherapy sessions per month\",\n            \"Weekly soft tissue and manual therapy\",\n            \"Weekly strength and conditioning sessions\",\n            \"Daily access to GoPerform facilities\",\n            \"Use of specialist equipment (AlterG, GameReady, Normatec, Compex, Altitude training)\",\n            \"Online support\"\n          ]\n        },\n        \"idealFor\": {\n          \"label\": \"IDEAL FOR\",\n          \"description\": \"Individuals aiming for a full return to sports and competition.\"\n        }\n      },\n      \"elevate-program\": {\n        \"id\": \"elevate-program\",\n        \"title\": \"Elevate Programme\",\n        \"description\": [\n          \"World-class support for athletes and fitness enthusiasts to achieve their training goals.\",\n          \"Tailored training and comprehensive support with no minimum contract.\"\n        ],\n        \"price\": {\n          \"label\": \"PRICE\",\n          \"value\": \"£195/month\"\n        },\n        \"details\": {\n          \"label\": \"WHAT'S INCLUDED\",\n          \"items\": [\n            \"Individually tailored training programme via our app\",\n            \"Unlimited group strength & conditioning sessions\",\n            \"Unlimited group classes (circuits, boxing, Olympic lifting, mobility & core)\",\n            \"Regular performance testing (strength, power, body composition)\",\n            \"50% discount on VO2 Max and Resting Metabolic Rate testing\",\n            \"1x FREE sports massage per month\",\n            \"Weekly injury drop-in clinics\",\n            \"Full open gym access to our Performance Centre\",\n            \"Nutrition consultancy and support\",\n            \"20% discount on physiotherapy, soft tissue, and sports massage\",\n            \"Access to altitude training system and Alter-G treadmill\",\n            \"Full use of recovery equipment (Normatec, GameReady, Theragun)\",\n            \"GoPerform Training T-shirt\"\n          ]\n        },\n        \"idealFor\": {\n          \"label\": \"IDEAL FOR\",\n          \"description\": \"Athletes, runners, and fitness enthusiasts seeking structured support.\"\n        },\n        \"testimonial\": {\n          \"label\": \"TESTIMONIAL\",\n          \"quote\": \"There is nowhere else like it in the area... the support is amazing\",\n          \"author\": \"Elsa C.\",\n          \"role\": \"Personal Trainer | Runner\"\n        }\n      }\n    }\n  }\n}"
        }
    ]
}